drf_sideloading/__init__.py
drf_sideloading/mixins.py
drf_sideloading/schema.py
drf_sideloading/serializers.py
drf_sideloading-2.2.3.dist-info/AUTHORS.md
drf_sideloading-2.2.3.dist-info/LICENSE
drf_sideloading-2.2.3.dist-info/METADATA
drf_sideloading-2.2.3.dist-info/WHEEL
drf_sideloading-2.2.3.dist-info/top_level.txt
drf_sideloading-2.2.3.dist-info/RECORD
